snick/__init__.py
snick/methods.py
snick/py.typed
snick-2.2.0.dist-info/METADATA
snick-2.2.0.dist-info/WHEEL
snick-2.2.0.dist-info/licenses/LICENSE.md
snick-2.2.0.dist-info/RECORD
