Metadata-Version: 2.4
Name: snick
Version: 2.2.0
Summary: Text gadgets that help with indentation
Project-URL: homepage, https://github.com/dusktreader/snick
Project-URL: source, https://github.com/dusktreader/snick
Project-URL: changelog, https://github.com/dusktreader/snick/blob/main/CHANGELOG.md
Author-email: Tucker Beck <tucker.beck@gmail.com>
License-Expression: MIT
License-File: LICENSE.md
Requires-Python: >=3.9
Requires-Dist: pprintpp~=0.4
